{
  "stars": [
    {
      "x": 0.8339230049875311,
      "y": 0.4288235489993673
    },
    {
      "x": 0.6583619077306733,
      "y": 0.37767640105224604
    },
    {
      "x": 0.5207060473815461,
      "y": 0.30436548899470545
    },
    {
      "x": 0.4508806109725686,
      "y": 0.31459491858412975
    },
    {
      "x": 0.4209554239401496,
      "y": 0.2958409643368519
    },
    {
      "x": 0.3870402119700748,
      "y": 0.30095567913156407
    },
    {
      "x": 0.21945916458852868,
      "y": 0.3947254503679531
    },
    {
      "x": 0.19751402743142144,
      "y": 0.4765608870833472
    },
    {
      "x": 0.07382325436408978,
      "y": 0.5430521794146049
    },
    {
      "x": 0.3212048004987531,
      "y": 0.4117744996836602
    },
    {
      "x": 0.3431499376558603,
      "y": 0.5038393659884786
    },
    {
      "x": 0.2733245012468828,
      "y": 0.5976091372248676
    },
    {
      "x": 0.4808057980049875,
      "y": 0.4049548799573774
    },
    {
      "x": 0.5286860972568579,
      "y": 0.4936099363990543
    }
  ],
  "lines": [
    [
      0,
      1
    ],
    [
      2,
      1
    ],
    [
      3,
      2
    ],
    [
      4,
      3
    ],
    [
      5,
      4
    ],
    [
      6,
      5
    ],
    [
      7,
      6
    ],
    [
      8,
      7
    ],
    [
      9,
      5
    ],
    [
      10,
      9
    ],
    [
      11,
      10
    ],
    [
      12,
      2
    ],
    [
      13,
      12
    ]
  ]
}