{
  "stars": [
    {
      "x": 0.7960177680798005,
      "y": 0.6300023309247111
    },
    {
      "x": 0.5386611596009975,
      "y": 0.35380773201025606
    },
    {
      "x": 0.36310006234413966,
      "y": 0.3503979221471146
    },
    {
      "x": 0.22145417705735662,
      "y": 0.27367720022643266
    },
    {
      "x": 0.42694046134663344,
      "y": 0.23957910159501847
    }
  ],
  "lines": [
    [
      0,
      1
    ],
    [
      1,
      2
    ],
    [
      2,
      3
    ],
    [
      3,
      4
    ],
    [
      1,
      4
    ]
  ]
}