{
  "stars": [
    {
      "x": 0.5346711346633416,
      "y": 0.14282574672838066
    },
    {
      "x": 0.5466412094763092,
      "y": 0.20420232426492624
    },
    {
      "x": 0.5227010598503741,
      "y": 0.28774266591189107
    },
    {
      "x": 0.6224516832917706,
      "y": 0.27069361659618396
    },
    {
      "x": 0.552626246882793,
      "y": 0.376397722353568
    },
    {
      "x": 0.5805564214463841,
      "y": 0.45823315906896206
    },
    {
      "x": 0.6164666458852868,
      "y": 0.49744597249508843
    },
    {
      "x": 0.3611050498753117,
      "y": 0.5213146415370784
    },
    {
      "x": 0.37507013715710724,
      "y": 0.6065598881156139
    },
    {
      "x": 0.41696539900249374,
      "y": 0.688395324831008
    },
    {
      "x": 0.4708307356608479,
      "y": 0.6679364656521595
    },
    {
      "x": 0.5027509351620948,
      "y": 0.20931703905963836
    },
    {
      "x": 0.45686564837905236,
      "y": 0.30138190536445675
    },
    {
      "x": 0.3990102867830424,
      "y": 0.35593886317471946
    },
    {
      "x": 0.25935941396508727,
      "y": 0.3593486730378609
    },
    {
      "x": 0.2912796134663342,
      "y": 0.3150211448170224
    }
  ],
  "lines": [
    [
      0,
      1
    ],
    [
      1,
      2
    ],
    [
      2,
      3
    ],
    [
      2,
      4
    ],
    [
      4,
      5
    ],
    [
      5,
      6
    ],
    [
      5,
      7
    ],
    [
      7,
      8
    ],
    [
      8,
      9
    ],
    [
      9,
      10
    ],
    [
      0,
      11
    ],
    [
      11,
      12
    ],
    [
      12,
      13
    ],
    [
      7,
      13
    ],
    [
      13,
      14
    ],
    [
      14,
      15
    ]
  ]
}